XJTU_TGA/__init__.py
XJTU_TGA/config.json
XJTU_TGA/TGAanalyser/DataPloter.py
XJTU_TGA/TGAanalyser/DataProcessor.py
XJTU_TGA/TGAanalyser/__init__.py
XJTU_TGA/dataset/ck.txt
XJTU_TGA/dataset/error.txt
XJTU_TGA/dataset/fcy.txt
XJTU_TGA/dataset/fcy1.txt
XJTU_TGA/dataset/fcy2.txt
XJTU_TGA/dataset/pzc.txt
XJTU_TGA/dataset/tjh.txt
XJTU_TGA/dataset/wll.txt
XJTU_TGA/dataset/ymt.txt
XJTU_TGA/dataset/zdw.txt
XJTU_TGA/dataset/zjz.txt
XJTU_TGA/plot/DTG-T.html
XJTU_TGA/plot/DTG-T.jpg
XJTU_TGA/plot/DTG-TG-T.html
XJTU_TGA/plot/DTG-TG-T.jpg
XJTU_TGA/plot/DTG_keypoint_select.jpg
XJTU_TGA/plot/DTG_param_select.jpg
XJTU_TGA/plot/DTG_range_select.jpg
XJTU_TGA/plot/TG-T.html
XJTU_TGA/plot/TG-T.jpg
XJTU_TGA/template/filter_choose.html
XJTU_TGA/template/help.html
XJTU_TGA/template/index.html
XJTU_TGA/template/logo.png
XJTU_TGA/template/plotly-latest.min.js
XJTU_TGA/template/point_choose.html
XJTU_TGA/template/qwebchannel.js
XJTU_TGA/template/range_choose.html
XJTU_TGA/template/image/1.png
XJTU_TGA/template/image/10.jpg
XJTU_TGA/template/image/11.jpg
XJTU_TGA/template/image/12.jpg
XJTU_TGA/template/image/13.jpg
XJTU_TGA/template/image/2.png
XJTU_TGA/template/image/3.png
XJTU_TGA/template/image/4.png
XJTU_TGA/template/image/5.png
XJTU_TGA/template/image/6.png
XJTU_TGA/template/image/7.png
XJTU_TGA/template/image/8.jpg
XJTU_TGA/template/image/9.jpg
XJTU_TGA/user_data/ck.json
XJTU_TGA/user_data/fcy.json
XJTU_TGA/user_data/tjh.json
XJTU_TGA/user_data/ymt.json
XJTU_TGA/user_data/zdw.json
XJTU_TGA-0.1.10.dist-info/LICENSE
XJTU_TGA-0.1.10.dist-info/METADATA
XJTU_TGA-0.1.10.dist-info/WHEEL
XJTU_TGA-0.1.10.dist-info/top_level.txt
XJTU_TGA-0.1.10.dist-info/RECORD
