Metadata-Version: 2.1
Name: XJTU-TGA
Version: 0.1.10
Classifier: Programming Language :: Python :: 3
Classifier: License :: OSI Approved :: MIT License
Classifier: Operating System :: OS Independent
Requires-Python: >=3.6
License-File: LICENSE
Requires-Dist: numpy (>=1.21.0)
Requires-Dist: scipy (>=1.7.0)
Requires-Dist: pandas (>=1.3.0)
Requires-Dist: PyQt5 (>=5.15.0)
Requires-Dist: PyQtWebEngine (>=5.15.0)
Requires-Dist: plotly (>=5.0.0)
